.coveragerc
.mailmap
.stestr.conf
.zuul.yaml
AUTHORS
CONTRIBUTING.rst
ChangeLog
HACKING.rst
LICENSE
MAINTAINERS
README.rst
babel.cfg
bindep.txt
requirements.txt
setup.cfg
setup.py
test-requirements.txt
tests-functional-py3.txt
tests-py3.txt
tox.ini
api-guide/source/authentication.rst
api-guide/source/conf.py
api-guide/source/extensions.rst
api-guide/source/extra_specs_and_properties.rst
api-guide/source/faults.rst
api-guide/source/general_info.rst
api-guide/source/index.rst
api-guide/source/limits.rst
api-guide/source/links_and_references.rst
api-guide/source/microversions.rst
api-guide/source/paginated_collections.rst
api-guide/source/polling_changes-since_parameter.rst
api-guide/source/request_and_response_formats.rst
api-guide/source/server_concepts.rst
api-guide/source/users.rst
api-guide/source/versions.rst
api-ref/source/conf.py
api-ref/source/diagnostics.inc
api-ref/source/extensions.inc
api-ref/source/flavors.inc
api-ref/source/images.inc
api-ref/source/index.rst
api-ref/source/ips.inc
api-ref/source/limits.inc
api-ref/source/metadata.inc
api-ref/source/os-agents.inc
api-ref/source/os-aggregates.inc
api-ref/source/os-assisted-volume-snapshots.inc
api-ref/source/os-availability-zone.inc
api-ref/source/os-baremetal-nodes.inc
api-ref/source/os-cells.inc
api-ref/source/os-certificates.inc
api-ref/source/os-cloudpipe.inc
api-ref/source/os-consoles.inc
api-ref/source/os-fixed-ips.inc
api-ref/source/os-flavor-access.inc
api-ref/source/os-flavor-extra-specs.inc
api-ref/source/os-floating-ip-dns.inc
api-ref/source/os-floating-ip-pools.inc
api-ref/source/os-floating-ips-bulk.inc
api-ref/source/os-floating-ips.inc
api-ref/source/os-fping.inc
api-ref/source/os-hosts.inc
api-ref/source/os-hypervisors.inc
api-ref/source/os-instance-actions.inc
api-ref/source/os-instance-usage-audit-log.inc
api-ref/source/os-interface.inc
api-ref/source/os-keypairs.inc
api-ref/source/os-migrations.inc
api-ref/source/os-networks.inc
api-ref/source/os-quota-class-sets.inc
doc/api_samples/extension-info/extensions-get-resp.json
doc/api_samples/extension-info/extensions-list-resp-v21-compatible.json
doc/api_samples/extension-info/extensions-list-resp.json
nova.egg-info/PKG-INFO
nova.egg-info/SOURCES.txt
nova.egg-info/dependency_links.txt
nova.egg-info/entry_points.txt
nova.egg-info/not-zip-safe
nova.egg-info/pbr.json
nova.egg-info/requires.txt
nova.egg-info/top_level.txt
nova/tests/functional/api_sample_tests/api_samples/extension-info/extensions-get-resp.json.tpl
nova/tests/functional/api_sample_tests/api_samples/extension-info/extensions-list-resp-v21-compatible.json.tpl
nova/tests/functional/api_sample_tests/api_samples/extension-info/extensions-list-resp.json.tpl
